screenbase/__init__.py
screenbase/cli.py
screenbase/watchers.py
screenbase-1.1.0.dist-info/DESCRIPTION.rst
screenbase-1.1.0.dist-info/METADATA
screenbase-1.1.0.dist-info/RECORD
screenbase-1.1.0.dist-info/WHEEL
screenbase-1.1.0.dist-info/entry_points.txt
screenbase-1.1.0.dist-info/metadata.json
screenbase-1.1.0.dist-info/top_level.txt
