Metadata-Version: 2.0
Name: screenbase
Version: 1.1.0
Summary: Tool for automatically copying screenshots into your Keybase public folder
Home-page: https://github.com/jlindsey/screenbase
Author: Josh Lindsey
Author-email: joshua.s.lindsey@gmail.com
License: GPL-3.0+
Keywords: screenshots keybase
Platform: UNKNOWN
Classifier: Development Status :: 5 - Production/Stable
Classifier: Environment :: Console
Classifier: Intended Audience :: Developers
Classifier: License :: OSI Approved :: GNU General Public License v3 or later (GPLv3+)
Classifier: Programming Language :: Python :: 2.7
Classifier: Topic :: Utilities
Requires-Dist: PyYAML (>=3.12)
Requires-Dist: pyperclip (>=1.5.27)
Requires-Dist: watchdog (>=0.8.2)
